algmatch/__init__.py
algmatch/hospitalResidentsProblem.py
algmatch/hospitalResidentsProblemWithTies.py
algmatch/stableMarriageProblem.py
algmatch/stableMarriageProblemWithTies.py
algmatch/stableRoommatesProblem.py
algmatch/studentProjectAllocation.py
algmatch/studentProjectAllocationProjects.py
algmatch/studentProjectAllocationWithTies.py
algmatch/abstractClasses/abstractPreferenceInstance.py
algmatch/abstractClasses/abstractPreferenceInstanceWithTies.py
algmatch/abstractClasses/abstractReader.py
algmatch/errors/InstanceSetupErrors.py
algmatch/errors/ReaderErrors.py
algmatch/stableMatchings/hospitalResidentsProblem/noTies/dictionaryReader.py
algmatch/stableMatchings/hospitalResidentsProblem/noTies/fileReader.py
algmatch/stableMatchings/hospitalResidentsProblem/noTies/hrAbstract.py
algmatch/stableMatchings/hospitalResidentsProblem/noTies/hrHospitalOptimal.py
algmatch/stableMatchings/hospitalResidentsProblem/noTies/hrPreferenceInstance.py
algmatch/stableMatchings/hospitalResidentsProblem/noTies/hrResidentOptimal.py
algmatch/stableMatchings/hospitalResidentsProblem/ties/dictionaryReader.py
algmatch/stableMatchings/hospitalResidentsProblem/ties/fileReader.py
algmatch/stableMatchings/hospitalResidentsProblem/ties/hrtAbstract.py
algmatch/stableMatchings/hospitalResidentsProblem/ties/hrtPreferenceInstance.py
algmatch/stableMatchings/hospitalResidentsProblem/ties/hrtStrongAbstract.py
algmatch/stableMatchings/hospitalResidentsProblem/ties/hrtStrongHospitalOptimal.py
algmatch/stableMatchings/hospitalResidentsProblem/ties/hrtStrongResidentOptimal.py
algmatch/stableMatchings/hospitalResidentsProblem/ties/hrtSuperHospitalOptimal.py
algmatch/stableMatchings/hospitalResidentsProblem/ties/hrtSuperResidentOptimal.py
algmatch/stableMatchings/stableMarriageProblem/noTies/dictionaryReader.py
algmatch/stableMatchings/stableMarriageProblem/noTies/fileReader.py
algmatch/stableMatchings/stableMarriageProblem/noTies/smAbstract.py
algmatch-1.4.0.dist-info/METADATA
algmatch-1.4.0.dist-info/WHEEL
algmatch-1.4.0.dist-info/licenses/LICENSE
algmatch-1.4.0.dist-info/RECORD
