Metadata-Version: 2.4
Name: algmatch
Version: 1.4.0
Summary: A package containing various matching algorithms, such as stable marriage, hospital-residents, and student-project allocation including the cases with ties/indifference.
Project-URL: Homepage, https://github.com/BenOnTheBoard/algmatch
Project-URL: Issues, https://github.com/BenOnTheBoard/algmatch/issues
Author-email: Ben Whitehead <ben.pi.whitehead@gmail.com>, Varad Kulkarni <varadkulk123@gmail.com>, Sofiat Olaosebikan <sofiat.olaosebikan@glasgow.ac.uk>
License-File: LICENSE
Classifier: License :: OSI Approved :: MIT License
Classifier: Operating System :: OS Independent
Classifier: Programming Language :: Python :: 3
Requires-Python: >=3.10
Requires-Dist: gurobipy
Requires-Dist: numpy>=1.21.5
Requires-Dist: tqdm==4.57.0
